pandassta/__init__.py
pandassta/df.py
pandassta/logging_constants.py
pandassta/sta.py
pandassta/sta_requests.py
pandassta-0.0.18.dist-info/METADATA
pandassta-0.0.18.dist-info/WHEEL
pandassta-0.0.18.dist-info/licenses/LICENSE
pandassta-0.0.18.dist-info/RECORD
