Metadata-Version: 2.4
Name: pandassta
Version: 0.0.18
Summary: Package for easy datarequests from sensortings
Project-URL: Homepage, https://github.com/nvdsteen/pandassta
Project-URL: Issues, https://github.com/nvdsteen/pandassta/issues
Author: nvds
License-File: LICENSE
Classifier: License :: OSI Approved :: GNU Affero General Public License v3
Classifier: Operating System :: OS Independent
Classifier: Programming Language :: Python :: 3
Requires-Python: >=3.11
Requires-Dist: geopandas==1.0.1
Requires-Dist: geopy==2.4.1
Requires-Dist: hatchling==1.27.0
Requires-Dist: hydra-core==1.3.2
Requires-Dist: numpy==2.2.3
Requires-Dist: omegaconf==2.3.0
Requires-Dist: ordered-enum==0.0.9
Requires-Dist: pandas==2.2.3
Requires-Dist: pytest==8.3.5
Requires-Dist: requests==2.32.3
Requires-Dist: strenum==0.4.15
Requires-Dist: tqdm==4.67.1
Requires-Dist: twine==6.1.0
